getsshpubkey/__init__.py
getsshpubkey/_version.py
getsshpubkey/handlers.py
getsshpubkey/labextension/package.json
getsshpubkey/labextension/schemas/getsshpubkey/package.json.orig
getsshpubkey/labextension/schemas/getsshpubkey/plugin.json
getsshpubkey/labextension/static/747.ed8b6d387d9ede33befa.js
getsshpubkey/labextension/static/763.640217bab87aaa49253c.js
getsshpubkey/labextension/static/remoteEntry.e26ebce8345489b3d227.js
getsshpubkey/labextension/static/style.js
getsshpubkey/labextension/static/third-party-licenses.json
getsshpubkey-1.0.0.data/data/etc/jupyter/jupyter_notebook_config.d/getsshpubkey.json
getsshpubkey-1.0.0.data/data/etc/jupyter/jupyter_server_config.d/getsshpubkey.json
getsshpubkey-1.0.0.data/data/share/jupyter/labextensions/getsshpubkey/install.json
getsshpubkey-1.0.0.data/data/share/jupyter/labextensions/getsshpubkey/package.json
getsshpubkey-1.0.0.data/data/share/jupyter/labextensions/getsshpubkey/schemas/getsshpubkey/package.json.orig
getsshpubkey-1.0.0.data/data/share/jupyter/labextensions/getsshpubkey/schemas/getsshpubkey/plugin.json
getsshpubkey-1.0.0.data/data/share/jupyter/labextensions/getsshpubkey/static/747.ed8b6d387d9ede33befa.js
getsshpubkey-1.0.0.data/data/share/jupyter/labextensions/getsshpubkey/static/763.640217bab87aaa49253c.js
getsshpubkey-1.0.0.data/data/share/jupyter/labextensions/getsshpubkey/static/remoteEntry.e26ebce8345489b3d227.js
getsshpubkey-1.0.0.data/data/share/jupyter/labextensions/getsshpubkey/static/style.js
getsshpubkey-1.0.0.data/data/share/jupyter/labextensions/getsshpubkey/static/third-party-licenses.json
getsshpubkey-1.0.0.dist-info/LICENSE
getsshpubkey-1.0.0.dist-info/METADATA
getsshpubkey-1.0.0.dist-info/WHEEL
getsshpubkey-1.0.0.dist-info/top_level.txt
getsshpubkey-1.0.0.dist-info/RECORD
